fbtool/__init__.py
fbtool/cli.py
facebook_apps_tool-0.0.4.dist-info/METADATA
facebook_apps_tool-0.0.4.dist-info/WHEEL
facebook_apps_tool-0.0.4.dist-info/entry_points.txt
facebook_apps_tool-0.0.4.dist-info/top_level.txt
facebook_apps_tool-0.0.4.dist-info/RECORD
